odoo/addons/web_switch_context_warning/README.rst
odoo/addons/web_switch_context_warning/__init__.py
odoo/addons/web_switch_context_warning/__manifest__.py
odoo/addons/web_switch_context_warning/i18n/es.po
odoo/addons/web_switch_context_warning/i18n/web_switch_company_warning.pot
odoo/addons/web_switch_context_warning/i18n/web_switch_context_warning.pot
odoo/addons/web_switch_context_warning/readme/CONTRIBUTORS.rst
odoo/addons/web_switch_context_warning/readme/DESCRIPTION.rst
odoo/addons/web_switch_context_warning/readme/ROADMAP.rst
odoo/addons/web_switch_context_warning/readme/USAGE.rst
odoo/addons/web_switch_context_warning/static/description/icon.png
odoo/addons/web_switch_context_warning/static/description/index.html
odoo/addons/web_switch_context_warning/static/src/js/switch_company_warning.js
odoo/addons/web_switch_context_warning/static/src/js/switch_company_warning_worker.js
odoo/addons/web_switch_context_warning/static/src/xml/switch_company_warning.xml
odoo/addons/web_switch_context_warning/view/view.xml
odoo11_addon_web_switch_context_warning-11.0.1.0.0.99.dev5.dist-info/METADATA
odoo11_addon_web_switch_context_warning-11.0.1.0.0.99.dev5.dist-info/WHEEL
odoo11_addon_web_switch_context_warning-11.0.1.0.0.99.dev5.dist-info/top_level.txt
odoo11_addon_web_switch_context_warning-11.0.1.0.0.99.dev5.dist-info/RECORD
